[{"id":1,"name":"\u8d85\u7ea7\u7ba1\u7406\u5458","status":1,"super":1,"description":"\u8d85\u7ea7\u7ba1\u7406\u5458","created_at":"2018-07-04 10:06:52","updated_at":"2018-07-04 10:06:52"},{"id":2,"name":"\u8ba2\u5355\u7ba1\u7406\u5458","status":1,"super":0,"description":"\u8ba2\u5355\u7ba1\u7406\u5458007","created_at":"2018-07-04 10:06:53","updated_at":"2018-07-04 10:07:24"},{"id":3,"name":"\u5546\u5bb6\u5ba1\u6838\u5458","status":1,"super":0,"description":"\u5546\u5bb6\u5ba1\u6838\u54582","created_at":"2018-09-27 17:49:51","updated_at":"2018-09-27 17:49:56"}]